setup.py
can_you_guess/__init__.py
can_you_guess/guess.py
can_you_guess.egg-info/PKG-INFO
can_you_guess.egg-info/SOURCES.txt
can_you_guess.egg-info/dependency_links.txt
can_you_guess.egg-info/not-zip-safe
can_you_guess.egg-info/top_level.txt