Metadata-Version: 1.0
Name: can-you-guess
Version: 0.1
Summary: Guess a number
Home-page: UNKNOWN
Author: John Anisere
Author-email: johnanisere@gmail.com
License: UNKNOWN
Platform: UNKNOWN
